<?xml version='1.0' encoding='utf-8'?>
<annotation>
  <folder>VOC2007</folder>
  <filename>domain1/100219.jpg</filename>
  <segmented>0</segmented>
  <size>
    <width>294</width>
    <height>243</height>
    <depth>3</depth>
  </size>
  <object>
    <name>powerbank</name>
    <pose>Unspecified</pose>
    <truncated>0</truncated>
    <difficult>0</difficult>
    <bndbox>
      <xmin>36</xmin>
      <ymin>13</ymin>
      <xmax>215</xmax>
      <ymax>130</ymax>
    </bndbox>
  </object>
  <object>
    <name>lighter</name>
    <pose>Unspecified</pose>
    <truncated>0</truncated>
    <difficult>0</difficult>
    <bndbox>
      <xmin>2</xmin>
      <ymin>76</ymin>
      <xmax>28</xmax>
      <ymax>149</ymax>
    </bndbox>
  </object>
</annotation>