<?xml version='1.0' encoding='utf-8'?>
<annotation>
  <folder>VOC2007</folder>
  <filename>domain2/200248.jpg</filename>
  <segmented>0</segmented>
  <size>
    <width>788</width>
    <height>512</height>
    <depth>3</depth>
  </size>
  <object>
    <name>powerbank</name>
    <pose>Unspecified</pose>
    <truncated>0</truncated>
    <difficult>0</difficult>
    <check>0</check>
    <bndbox>
      <xmin>237</xmin>
      <ymin>370</ymin>
      <xmax>321</xmax>
      <ymax>465</ymax>
    </bndbox>
  </object>
  <object>
    <name>lighter</name>
    <pose>Unspecified</pose>
    <truncated>0</truncated>
    <difficult>0</difficult>
    <check>0</check>
    <bndbox>
      <xmin>64</xmin>
      <ymin>175</ymin>
      <xmax>124</xmax>
      <ymax>234</ymax>
    </bndbox>
  </object>
</annotation>