<?xml version='1.0' encoding='utf-8'?>
<annotation>
  <folder>VOC2007</folder>
  <filename>domain3/300032.jpg</filename>
  <segmented>0</segmented>
  <size>
    <width>653</width>
    <height>410</height>
    <depth>3</depth>
  </size>
  <object>
    <name>lighter</name>
    <pose>Unspecified</pose>
    <truncated>1</truncated>
    <difficult>0</difficult>
    <bndbox>
      <xmin>538</xmin>
      <ymin>303</ymin>
      <xmax>588</xmax>
      <ymax>408</ymax>
    </bndbox>
  </object>
  <object>
    <name>lighter</name>
    <pose>Unspecified</pose>
    <truncated>0</truncated>
    <difficult>0</difficult>
    <bndbox>
      <xmin>419</xmin>
      <ymin>277</ymin>
      <xmax>491</xmax>
      <ymax>366</ymax>
    </bndbox>
  </object>
</annotation>