<?xml version='1.0' encoding='utf-8'?>
<annotation>
  <folder>VOC2007</folder>
  <filename>domain3/300101.jpg</filename>
  <segmented>0</segmented>
  <size>
    <width>1013</width>
    <height>485</height>
    <depth>3</depth>
  </size>
  <object>
    <name>lighter</name>
    <pose>Unspecified</pose>
    <truncated>0</truncated>
    <difficult>0</difficult>
    <bndbox>
      <xmin>420</xmin>
      <ymin>189</ymin>
      <xmax>539</xmax>
      <ymax>226</ymax>
    </bndbox>
  </object>
  </annotation>