<?xml version='1.0' encoding='utf-8'?>
<annotation>
  <folder>VOC2007</folder>
  <filename>domain4/400219.jpg</filename>
  <segmented>0</segmented>
  <size>
    <width>1118</width>
    <height>700</height>
    <depth>3</depth>
  </size>
  <object>
    <name>knife</name>
    <pose>Unspecified</pose>
    <truncated>0</truncated>
    <difficult>0</difficult>
    <check>0</check>
    <bndbox>
      <xmin>1001.1500096177663</xmin>
      <ymin>27.384821667988305</ymin>
      <xmax>1112</xmax>
      <ymax>254</ymax>
    </bndbox>
  </object>
  <object>
    <name>lighter</name>
    <pose>Unspecified</pose>
    <truncated>0</truncated>
    <difficult>0</difficult>
    <check>0</check>
    <bndbox>
      <xmin>969.1879369835158</xmin>
      <ymin>43.82553814551501</ymin>
      <xmax>1003</xmax>
      <ymax>158</ymax>
    </bndbox>
  </object>
  <object>
    <name>knife</name>
    <pose>Unspecified</pose>
    <truncated>0</truncated>
    <difficult>0</difficult>
    <check>0</check>
    <bndbox>
      <xmin>240.29198467410052</xmin>
      <ymin>185.94800964221832</ymin>
      <xmax>454</xmax>
      <ymax>468</ymax>
    </bndbox>
  </object>
  <object>
    <name>knife</name>
    <pose>Unspecified</pose>
    <truncated>0</truncated>
    <difficult>0</difficult>
    <check>0</check>
    <bndbox>
      <xmin>140.35419198759624</xmin>
      <ymin>299.8869699014674</ymin>
      <xmax>178</xmax>
      <ymax>434</ymax>
    </bndbox>
  </object>
  <object>
    <name>lighter</name>
    <pose>Unspecified</pose>
    <truncated>0</truncated>
    <difficult>0</difficult>
    <check>0</check>
    <bndbox>
      <xmin>987.5896960317727</xmin>
      <ymin>299.01614909650533</ymin>
      <xmax>1032</xmax>
      <ymax>421</ymax>
    </bndbox>
  </object>
</annotation>