<?xml version='1.0' encoding='utf-8'?>
<annotation>
  <folder>VOC2007</folder>
  <filename>domain4/400339.jpg</filename>
  <segmented>0</segmented>
  <size>
    <width>727</width>
    <height>594</height>
    <depth>3</depth>
  </size>
  <object>
    <name>scissors</name>
    <pose>Unspecified</pose>
    <truncated>0</truncated>
    <difficult>0</difficult>
    <bndbox>
      <xmin>511</xmin>
      <ymin>266</ymin>
      <xmax>680</xmax>
      <ymax>554</ymax>
    </bndbox>
  </object>
  <object>
    <name>slingshot</name>
    <pose>Unspecified</pose>
    <truncated>0</truncated>
    <difficult>0</difficult>
    <bndbox>
      <xmin>470</xmin>
      <ymin>261</ymin>
      <xmax>623</xmax>
      <ymax>479</ymax>
    </bndbox>
  </object>
  <object>
    <name>knife</name>
    <pose>Unspecified</pose>
    <truncated>0</truncated>
    <difficult>0</difficult>
    <bndbox>
      <xmin>565</xmin>
      <ymin>270</ymin>
      <xmax>641</xmax>
      <ymax>413</ymax>
    </bndbox>
  </object>
</annotation>