<?xml version='1.0' encoding='utf-8'?>
<annotation>
  <folder>VOC2007</folder>
  <filename>domain4/400505.jpg</filename>
  <segmented>0</segmented>
  <size>
    <width>896</width>
    <height>700</height>
    <depth>3</depth>
  </size>
  <object>
    <name>knife</name>
    <pose>Unspecified</pose>
    <truncated>0</truncated>
    <difficult>0</difficult>
    <bndbox>
      <xmin>368</xmin>
      <ymin>35</ymin>
      <xmax>479</xmax>
      <ymax>431</ymax>
    </bndbox>
  </object>
  </annotation>