<?xml version='1.0' encoding='utf-8'?>
<VpSizeADD>
  <folder>VOC2007</folder>
  <filename>domain5/500238.jpg</filename>
  <segmented>0</segmented>
  <size>
    <width>804</width>
    <height>500</height>
    <depth>3</depth>
  </size>
  <object>
    <name>knife</name>
    <pose>Unspecified</pose>
    <truncated>0</truncated>
    <difficult>0</difficult>
    <bndbox>
      <xmin>543</xmin>
      <ymin>64</ymin>
      <xmax>608</xmax>
      <ymax>230</ymax>
    </bndbox>
  </object>
  <object>
    <name>knife</name>
    <pose>Unspecified</pose>
    <truncated>0</truncated>
    <difficult>0</difficult>
    <bndbox>
      <xmin>248</xmin>
      <ymin>130</ymin>
      <xmax>384</xmax>
      <ymax>176</ymax>
    </bndbox>
  </object>
  <object>
    <name>knife</name>
    <pose>Unspecified</pose>
    <truncated>0</truncated>
    <difficult>0</difficult>
    <bndbox>
      <xmin>152</xmin>
      <ymin>276</ymin>
      <xmax>257</xmax>
      <ymax>324</ymax>
    </bndbox>
  </object>
  <VpSize>
    <Xmin>83</Xmin>
    <Ymin>30</Ymin>
    <Xmax>646</Xmax>
    <Ymax>468</Ymax>
  </VpSize>
</VpSizeADD>