<?xml version='1.0' encoding='utf-8'?>
<annotation>
  <folder>VOC2007</folder>
  <filename>domain6/600083.jpg</filename>
  <segmented>0</segmented>
  <size>
    <width>700</width>
    <height>300</height>
    <depth>3</depth>
  </size>
  <object>
    <name>zippooil</name>
    <pose>Unspecified</pose>
    <truncated>0</truncated>
    <difficult>0</difficult>
    <bndbox>
      <xmin>345</xmin>
      <ymin>135</ymin>
      <xmax>396</xmax>
      <ymax>225</ymax>
    </bndbox>
  </object>
  <object>
    <name>pressure</name>
    <pose>Unspecified</pose>
    <truncated>0</truncated>
    <difficult>0</difficult>
    <bndbox>
      <xmin>371</xmin>
      <ymin>54</ymin>
      <xmax>493</xmax>
      <ymax>135</ymax>
    </bndbox>
  </object>
  <object>
    <name>lighter</name>
    <pose>Unspecified</pose>
    <truncated>0</truncated>
    <difficult>0</difficult>
    <bndbox>
      <xmin>380</xmin>
      <ymin>88</ymin>
      <xmax>421</xmax>
      <ymax>144</ymax>
    </bndbox>
  </object>
  <object>
    <name>knife</name>
    <pose>Unspecified</pose>
    <truncated>0</truncated>
    <difficult>0</difficult>
    <bndbox>
      <xmin>490</xmin>
      <ymin>71</ymin>
      <xmax>544</xmax>
      <ymax>200</ymax>
    </bndbox>
  </object>
  <object>
    <name>knife</name>
    <pose>Unspecified</pose>
    <truncated>0</truncated>
    <difficult>0</difficult>
    <bndbox>
      <xmin>387</xmin>
      <ymin>102</ymin>
      <xmax>480</xmax>
      <ymax>233</ymax>
    </bndbox>
  </object>
</annotation>