<?xml version='1.0' encoding='utf-8'?>
<annotation>
  <folder>VOC2007</folder>
  <filename>domain6/600050.jpg</filename>
  <segmented>0</segmented>
  <size>
    <width>428</width>
    <height>420</height>
    <depth>3</depth>
  </size>
  <object>
    <name>powerbank</name>
    <pose>Unspecified</pose>
    <truncated>0</truncated>
    <difficult>0</difficult>
    <bndbox>
      <xmin>141</xmin>
      <ymin>228</ymin>
      <xmax>234</xmax>
      <ymax>337</ymax>
    </bndbox>
  </object>
  <object>
    <name>knife</name>
    <pose>Unspecified</pose>
    <truncated>0</truncated>
    <difficult>0</difficult>
    <bndbox>
      <xmin>122</xmin>
      <ymin>162</ymin>
      <xmax>178</xmax>
      <ymax>249</ymax>
    </bndbox>
  </object>
  <object>
    <name>knife</name>
    <pose>Unspecified</pose>
    <truncated>0</truncated>
    <difficult>0</difficult>
    <bndbox>
      <xmin>38</xmin>
      <ymin>203</ymin>
      <xmax>61</xmax>
      <ymax>293</ymax>
    </bndbox>
  </object>
</annotation>